arc_cache/__init__.py
arc_cache/decorator.py
arc_cache-0.1.1.dist-info/DESCRIPTION.rst
arc_cache-0.1.1.dist-info/METADATA
arc_cache-0.1.1.dist-info/RECORD
arc_cache-0.1.1.dist-info/WHEEL
arc_cache-0.1.1.dist-info/metadata.json
arc_cache-0.1.1.dist-info/pbr.json
arc_cache-0.1.1.dist-info/top_level.txt
