Metadata-Version: 2.0
Name: arc-cache
Version: 0.1.1
Summary: Memoization decorator using an adaptive replacement cache.
Home-page: https://github.com/jimjh/arc_cache
Author: James Lim
Author-email: jim@jimjh.com
License: MIT
Keywords: cache lru memoize arc
Platform: UNKNOWN
Classifier: Development Status :: 3 - Alpha
Classifier: Intended Audience :: Developers
Classifier: License :: OSI Approved :: MIT License
Classifier: Topic :: Software Development :: Libraries
Classifier: Programming Language :: Python :: 3
Classifier: Programming Language :: Python :: 3.2
Classifier: Programming Language :: Python :: 3.3
Classifier: Programming Language :: Python :: 3.4
